{
  "title": "The 100 Girlfriends Who Really, Really, Really, Really, Really Love You",
  "description": "Aijo Rentaro has asked a hundred girls out and struck out every time. In desperation, he prays for guidance, only to be told by a god that his rejections were due to a cosmic mishap! Now this god will set things right by making sure Aijo gets one hundred dates. Except, as things often go with gods, there’s a catch: each of his one hundred dates is Aijo’s destined soulmate! Worse, if he doesn’t return their feelings, they’ll all die in horrible - and hilarious - accidents!",
  "artist": "",
  "author": "",
  "cover": "https://i.imgur.com/DNs1Z0N.jpeg",
  "chapters": {
    "1": {
      "title": "chapter 1",
      "volume": "",
      "last_updated": "1774363909",
      "groups": {
        "": "/proxy/api/imgchest/chapter/dl7p635364o"
      }
    },
    "2": {
      "title": "chapter 2",
      "volume": "",
      "last_updated": "1774364205",
      "groups": {
        "": "/proxy/api/imgchest/chapter/9rydekngw4k"
      }
    },
    "3": {
      "title": "chapter 3",
      "volume": "",
      "last_updated": "1774380277",
      "groups": {
        "": "/proxy/api/imgchest/chapter/6eyr6ebb6yp"
      }
    },
    "4": {
      "title": "chapter 4",
      "volume": "",
      "last_updated": "1774380403",
      "groups": {
        "": "/proxy/api/imgchest/chapter/na7knjgpm78"
      }
    },
    "5": {
      "title": "chapter 5",
      "volume": "",
      "last_updated": "1774380587",
      "groups": {
        "": "/proxy/api/imgchest/chapter/na7knjglm78"
      }
    },
    "6": {
      "title": "chapter 6",
      "volume": "",
      "last_updated": "1774380982",
      "groups": {
        "": "/proxy/api/imgchest/chapter/vj4j6lza5y8"
      }
    },
    "7": {
      "title": "chapter 7",
      "volume": "",
      "last_updated": "1774381092",
      "groups": {
        "": "/proxy/api/imgchest/chapter/9p4n6rarw7n"
      }
    },
    "8": {
      "title": "chapter 8",
      "volume": "",
      "last_updated": "1774381309",
      "groups": {
        "": "/proxy/api/imgchest/chapter/vj4j6lzx5y8"
      }
    },
    "9": {
      "title": "chapter 9",
      "volume": "",
      "last_updated": "1774381445",
      "groups": {
        "": "/proxy/api/imgchest/chapter/qe4g8n3oo7j"
      }
    },
    "10": {
      "title": "chapter 10",
      "volume": "",
      "last_updated": "1774381642",
      "groups": {
        "": "/proxy/api/imgchest/chapter/9p4n6roez7n"
      }
    },
    "11": {
      "title": "chapter 11",
      "volume": "",
      "last_updated": "1774381761",
      "groups": {
        "": "/proxy/api/imgchest/chapter/qe4g8n9lr7j"
      }
    },
    "12": {
      "title": "chapter 12",
      "volume": "",
      "last_updated": "1774450589",
      "groups": {
        "": "/proxy/api/imgchest/chapter/6eyr6q8bgyp"
      }
    },
    "13": {
      "title": "chapter 13",
      "volume": "",
      "last_updated": "1774450704",
      "groups": {
        "": "/proxy/api/imgchest/chapter/md7ov2xkryp"
      }
    },
    "14": {
      "title": "chapter 14",
      "volume": "",
      "last_updated": "1774450830",
      "groups": {
        "": "/proxy/api/imgchest/chapter/qb4zrgj2d7j"
      }
    },
    "15": {
      "title": "chapter 15",
      "volume": "",
      "last_updated": "1774451088",
      "groups": {
        "": "/proxy/api/imgchest/chapter/m9yxqe2aq7q"
      }
    },
    "16": {
      "title": "chapter 16",
      "volume": "",
      "last_updated": "1774451217",
      "groups": {
        "": "/proxy/api/imgchest/chapter/o24amwvb24l"
      }
    },
    "17": {
      "title": "chapter 17",
      "volume": "",
      "last_updated": "1774451354",
      "groups": {
        "": "/proxy/api/imgchest/chapter/vj4j6xvbxy8"
      }
    },
    "18": {
      "title": "chapter 18",
      "volume": "",
      "last_updated": "1774451482",
      "groups": {
        "": "/proxy/api/imgchest/chapter/a8469ekjz4x"
      }
    },
    "19": {
      "title": "chapter 19",
      "volume": "",
      "last_updated": "1774451615",
      "groups": {
        "": "/proxy/api/imgchest/chapter/bp45nwzgn45"
      }
    },
    "20": {
      "title": "chapter 20",
      "volume": "",
      "last_updated": "1774451811",
      "groups": {
        "": "/proxy/api/imgchest/chapter/9rydegaga4k"
      }
    },
    "21": {
      "title": "chapter 21",
      "volume": "",
      "last_updated": "1774451944",
      "groups": {
        "": "/proxy/api/imgchest/chapter/9rydegava4k"
      }
    },
    "22": {
      "title": "chapter 22",
      "volume": "",
      "last_updated": "1774452068",
      "groups": {
        "": "/proxy/api/imgchest/chapter/na7kn9e3378"
      }
    },
    "23": {
      "title": "chapter 23",
      "volume": "",
      "last_updated": "1774531985",
      "groups": {
        "": "/proxy/api/imgchest/chapter/agyvl3kjb78"
      }
    },
    "24": {
      "title": "chapter 24",
      "volume": "",
      "last_updated": "1774532237",
      "groups": {
        "": "/proxy/api/imgchest/chapter/xny89gdr24b"
      }
    },
    "25": {
      "title": "chapter 25",
      "volume": "",
      "last_updated": "1774532351",
      "groups": {
        "": "/proxy/api/imgchest/chapter/5xy2gr9mz7l"
      }
    },
    "26": {
      "title": "chapter 26",
      "volume": "",
      "last_updated": "1774532494",
      "groups": {
        "": "/proxy/api/imgchest/chapter/pg738mn3o4r"
      }
    },
    "27": {
      "title": "chapter 27",
      "volume": "",
      "last_updated": "1774532648",
      "groups": {
        "": "/proxy/api/imgchest/chapter/5xy2gr9j37l"
      }
    },
    "28": {
      "title": "chapter 28",
      "volume": "",
      "last_updated": "1774532778",
      "groups": {
        "": "/proxy/api/imgchest/chapter/qb4zrgzbl7j"
      }
    },
    "29": {
      "title": "chapter 29",
      "volume": "",
      "last_updated": "1774532929",
      "groups": {
        "": "/proxy/api/imgchest/chapter/9rydegw964k"
      }
    },
    "30": {
      "title": "chapter 30",
      "volume": "",
      "last_updated": "1774533192",
      "groups": {
        "": "/proxy/api/imgchest/chapter/wl7l6nvb37x"
      }
    },
    "31": {
      "title": "chapter 31",
      "volume": "",
      "last_updated": "1774533354",
      "groups": {
        "": "/proxy/api/imgchest/chapter/agyvl3kkz78"
      }
    },
    "32": {
      "title": "chapter 32",
      "volume": "",
      "last_updated": "1774533474",
      "groups": {
        "": "/proxy/api/imgchest/chapter/6eyr6qjj6yp"
      }
    },
    "33": {
      "title": "chapter 33",
      "volume": "",
      "last_updated": "1774534946",
      "groups": {
        "": "/proxy/api/imgchest/chapter/xny89gdad4b"
      }
    },
    "34": {
      "title": "chapter 34",
      "volume": "",
      "last_updated": "1774618335",
      "groups": {
        "": "/proxy/api/imgchest/chapter/bp45naja245"
      }
    },
    "35": {
      "title": "chapter 35",
      "volume": "",
      "last_updated": "1774618444",
      "groups": {
        "": "/proxy/api/imgchest/chapter/vj4j6rjo2y8"
      }
    },
    "36": {
      "title": "chapter 36",
      "volume": "",
      "last_updated": "1774618553",
      "groups": {
        "": "/proxy/api/imgchest/chapter/ne7b38owjy5"
      }
    },
    "37": {
      "title": "chapter 37",
      "volume": "",
      "last_updated": "1774618802",
      "groups": {
        "": "/proxy/api/imgchest/chapter/92499o5jm4n"
      }
    },
    "38": {
      "title": "chapter 38",
      "volume": "",
      "last_updated": "1774618953",
      "groups": {
        "": "/proxy/api/imgchest/chapter/92499o5jm4n"
      }
    },
    "39": {
      "title": "chapter 39",
      "volume": "",
      "last_updated": "1774619067",
      "groups": {
        "": "/proxy/api/imgchest/chapter/dl7p6xw9p4o"
      }
    },
    "40": {
      "title": "chapter 40",
      "volume": "",
      "last_updated": "1774619195",
      "groups": {
        "": "/proxy/api/imgchest/chapter/lqyez9oqmyd"
      }
    },
    "41": {
      "title": "chapter 41",
      "volume": "",
      "last_updated": "1774619370",
      "groups": {
        "": "/proxy/api/imgchest/chapter/9p4n65mnb7n"
      }
    },
    "42": {
      "title": "chapter 42",
      "volume": "",
      "last_updated": "1774619651",
      "groups": {
        "": "/proxy/api/imgchest/chapter/9rydevo6a4k"
      }
    },
    "43": {
      "title": "chapter 43",
      "volume": "",
      "last_updated": "1774619791",
      "groups": {
        "": "/proxy/api/imgchest/chapter/9p4n65mjb7n"
      }
    },
    "44": {
      "title": "chapter 44",
      "volume": "",
      "last_updated": "1774707021",
      "groups": {
        "": "/proxy/api/imgchest/chapter/wl7llzwzx7x"
      }
    },
    "45": {
      "title": "chapter 45",
      "volume": "",
      "last_updated": "1774707167",
      "groups": {
        "": "/proxy/api/imgchest/chapter/xny8rp6p24b"
      }
    },
    "46": {
      "title": "chapter 46",
      "volume": "",
      "last_updated": "1774707296",
      "groups": {
        "": "/proxy/api/imgchest/chapter/ne7brg6gmy5"
      }
    },
    "47": {
      "title": "chapter 47",
      "volume": "",
      "last_updated": "1774707401",
      "groups": {
        "": "/proxy/api/imgchest/chapter/bp45jkoxny5"
      }
    },
    "48": {
      "title": "chapter 48",
      "volume": "",
      "last_updated": "1774707537",
      "groups": {
        "": "/proxy/api/imgchest/chapter/wl7llzwkx7x"
      }
    },
    "49": {
      "title": "chapter 49",
      "volume": "",
      "last_updated": "1774707665",
      "groups": {
        "": "/proxy/api/imgchest/chapter/o24adx6gd4l"
      }
    },
    "50": {
      "title": "chapter 50",
      "volume": "",
      "last_updated": "1774707843",
      "groups": {
        "": "/proxy/api/imgchest/chapter/9ryd3l2pa7k"
      }
    },
    "51": {
      "title": "chapter 51",
      "volume": "",
      "last_updated": "1774708367",
      "groups": {
        "": "/proxy/api/imgchest/chapter/vj4j5omq978"
      }
    },
    "52": {
      "title": "chapter 52",
      "volume": "",
      "last_updated": "1774708573",
      "groups": {
        "": "/proxy/api/imgchest/chapter/n87w8znlq7x"
      }
    },
    "53": {
      "title": "chapter 53",
      "volume": "",
      "last_updated": "1774708768",
      "groups": {
        "": "/proxy/api/imgchest/chapter/ej7mjzewa7d"
      }
    },
    "54": {
      "title": "chapter 54",
      "volume": "",
      "last_updated": "1774709008",
      "groups": {
        "": "/proxy/api/imgchest/chapter/6eyr3rnm6yp"
      }
    },
    "55": {
      "title": "chapter 55",
      "volume": "",
      "last_updated": "1774785965",
      "groups": {
        "": "/proxy/api/imgchest/chapter/qe4gzdlwr7j"
      }
    },
    "56": {
      "title": "chapter 56",
      "volume": "",
      "last_updated": "1774786096",
      "groups": {
        "": "/proxy/api/imgchest/chapter/wl7llxkop7x"
      }
    },
    "57": {
      "title": "chapter 57",
      "volume": "",
      "last_updated": "1774786318",
      "groups": {
        "": "/proxy/api/imgchest/chapter/9p4nqe2vz4n"
      }
    },
    "58": {
      "title": "chapter 58",
      "volume": "",
      "last_updated": "1774786492",
      "groups": {
        "": "/proxy/api/imgchest/chapter/wl7llxkaq7x"
      }
    },
    "5.5": {
      "title": "chapter 5.5",
      "volume": "",
      "last_updated": "1774380806",
      "groups": {
        "": "/proxy/api/imgchest/chapter/qb4zrxbov7j"
      }
    },
    "14.5": {
      "title": "chapter 14.5",
      "volume": "",
      "last_updated": "1774450970",
      "groups": {
        "": "/proxy/api/imgchest/chapter/vj4j6xvpxy8"
      }
    },
    "23.5": {
      "title": "chapter 23.5",
      "volume": "",
      "last_updated": "1774532113",
      "groups": {
        "": "/proxy/api/imgchest/chapter/ej7m6bxj94d"
      }
    },
    "32.5": {
      "title": "chapter 32.5",
      "volume": "",
      "last_updated": "1774533606",
      "groups": {
        "": "/proxy/api/imgchest/chapter/a8469ejjv4x"
      }
    },
    "41.5": {
      "title": "chapter 41.5",
      "volume": "",
      "last_updated": "1774619498",
      "groups": {
        "": "/proxy/api/imgchest/chapter/agyvlmaqb78"
      }
    },
    "50.5": {
      "title": "chapter 50.5",
      "volume": "",
      "last_updated": "1774708012",
      "groups": {
        "": "/proxy/api/imgchest/chapter/ljyqmgkzx72"
      }
    }
  }
}