{
  "title": "Spy x Family",
  "description": "The master spy codenamed Twilight has spent his days on undercover missions, all for the dream of a better world. But one day, he receives a particularly difficult new order from command. For his mission, he must form a temporary family and start a new life?! A Spy/Action/Comedy about a one-of-a-kind family!",
  "artist": "",
  "author": "",
  "cover": "https://i.imgur.com/5CSb94d.jpeg",
  "chapters": {
    "1": {
      "title": "chapter 1",
      "volume": "",
      "last_updated": "1779285797",
      "groups": {
        "": "/proxy/api/imgchest/chapter/agyva5wxzy8"
      }
    },
    "2": {
      "title": "chapter 2",
      "volume": "",
      "last_updated": "1779366766",
      "groups": {
        "": "/proxy/api/imgchest/chapter/ej7mrdxp94d"
      }
    },
    "3": {
      "title": "chapter 3",
      "volume": "",
      "last_updated": "1779366953",
      "groups": {
        "": "/proxy/api/imgchest/chapter/n87w2a35q7x"
      }
    },
    "4": {
      "title": "chapter 4",
      "volume": "",
      "last_updated": "1779367212",
      "groups": {
        "": "/proxy/api/imgchest/chapter/qe4gkngbk7j"
      }
    }
  }
}